Workbook

Sheet Executive Summary
A1: SATMIX DIGITAL INFRASTRUCTURE & APP DEVELOPMENT BUDGET
A2: Master 12-Month Financial Model & Cash Flow Projection | Prepared for CFO (Shashank Jajodia) by CTO (Veer Khanna)
A4: TOTAL 12M BUDGET | D4: PHASE 1 RUNWAY (M1-M4) | G4: PHASE 2 RUNWAY (M5-M12) | J4: WITH CLOUD CREDITS (EST.)
A5: =N18 -> 0 | D5: =SUM(B18:E18) -> 0 | G5: =SUM(F18:M18) -> 0 | J5: =N18-N20 -> -7397600
A8: Cost Category / Department | B8: M1 | C8: M2 | D8: M3 | E8: M4 | F8: M5 | G8: M6 | H8: M7 | I8: M8 | J8: M9 | K8: M10 | L8: M11 | M8: M12 | N8: 12-Month Total
A9: 1. Human Capital & Engineering Team | B9: ='Team Expansion'!B20 -> 0 | C9: ='Team Expansion'!C20 -> 0 | D9: ='Team Expansion'!D20 -> 0 | E9: ='Team Expansion'!E20 -> 0 | F9: ='Team Expansion'!F20 -> 0 | G9: ='Team Expansion'!G20 -> 245000 | H9: ='Team Expansion'!H20 -> 245000 | I9: ='Team Expansion'!I20 -> 245000 | ... M9: ='Team Expansion'!M20 -> 720000 | N9: =SUM(B9:M9) -> 3045000
A10: 2. Cloud Infrastructure & DevOps | B10: ='Cloud & Infra'!B12 -> 38000 | C10: ='Cloud & Infra'!C12 -> 38000 | D10: ='Cloud & Infra'!D12 -> 47000 | E10: ='Cloud & Infra'!E12 -> 54500 | F10: ='Cloud & Infra'!F12 -> 74000 | G10: ='Cloud & Infra'!G12 -> 89500 | H10: ='Cloud & Infra'!H12 -> 105000 | I10: ='Cloud & Infra'!I12 -> 105000 | ... M10: ='Cloud & Infra'!M12 -> 132000 | N10: =SUM(B10:M10) -> 1048000
A11: 3. Fintech APIs, KYC & Payment Rails | B11: ='Fintech APIs & Rails'!B14 -> 51000 | C11: ='Fintech APIs & Rails'!C14 -> 59000 | D11: ='Fintech APIs & Rails'!D14 -> 69000 | E11: ='Fintech APIs & Rails'!E14 -> 81000 | F11: ='Fintech APIs & Rails'!F14 -> 116500 | G11: ='Fintech APIs & Rails'!G14 -> 145000 | H11: ='Fintech APIs & Rails'!H14 -> 176500 | I11: ='Fintech APIs & Rails'!I14 -> 201000 | ... M11: ='Fintech APIs & Rails'!M14 -> 258500 | N11: =SUM(B11:M11) -> 1866000
A12: 4. Security Audits, VAPT & FIU Tooling | B12: ='Security & Compliance'!B12 -> 354500 | C12: ='Security & Compliance'!C12 -> 14500 | D12: ='Security & Compliance'!D12 -> 24500 | E12: ='Security & Compliance'!E12 -> 39500 | F12: ='Security & Compliance'!F12 -> 31500 | G12: ='Security & Compliance'!G12 -> 46500 | H12: ='Security & Compliance'!H12 -> 181500 | I12: ='Security & Compliance'!I12 -> 46500 | ... M12: ='Security & Compliance'!M12 -> 54500 | N12: =SUM(B12:M12) -> 927000
A13: 5. Developer Accounts & Software Licences | B13: ='Tooling & Licences'!B14 -> 44500 | C13: ='Tooling & Licences'!C14 -> 18500 | D13: ='Tooling & Licences'!D14 -> 18500 | E13: ='Tooling & Licences'!E14 -> 18500 | F13: ='Tooling & Licences'!F14 -> 30000 | G13: ='Tooling & Licences'!G14 -> 30000 | H13: ='Tooling & Licences'!H14 -> 30000 | I13: ='Tooling & Licences'!I14 -> 30000 | ... M13: ='Tooling & Licences'!M14 -> 30000 | N13: =SUM(B13:M13) -> 340000
A14: Operational Subtotal (Base) | B14: =SUM(B9:B13) -> 488000 | C14: =SUM(C9:C13) -> 130000 | D14: =SUM(D9:D13) -> 159000 | E14: =SUM(E9:E13) -> 193500 | F14: =SUM(F9:F13) -> 252000 | G14: =SUM(G9:G13) -> 556000 | H14: =SUM(H9:H13) -> 738000 | I14: =SUM(I9:I13) -> 627500 | ... N14: =SUM(N9:N13) -> 7226000
A15: 6. Contingency & Scale Buffer (10%) | B15: =B14*0.1 -> 48800 | C15: =C14*0.1 -> 13000 | D15: =D14*0.1 -> 15900 | E15: =E14*0.1 -> 19350 | F15: =F14*0.1 -> 25200 | G15: =G14*0.1 -> 55600 | H15: =H14*0.1 -> 73800 | I15: =I14*0.1 -> 62750 | ... M15: =M14*0.1 -> 119500 | N15: =SUM(B15:M15) -> 722600
A16: GROSS MONTHLY CASH BURN | B16: =B14+B15 -> 536800 | C16: =C14+C15 -> 143000 | D16: =D14+D15 -> 174900 | E16: =E14+E15 -> 212850 | F16: =F14+F15 -> 277200 | G16: =G14+G15 -> 611600 | H16: =H14+H15 -> 811800 | I16: =I14+I15 -> 690250 | ... N16: =N14+N15 -> 7948600
A17: Cumulative Cash Outlay | B17: =B16 -> 536800 | C17: =B17+C16 -> 679800 | D17: =C17+D16 -> 854700 | E17: =D17+E16 -> 1067550 | F17: =E17+F16 -> 1344750 | G17: =F17+G16 -> 1956350 | H17: =G17+H16 -> 2768150 | I17: =H17+I16 -> 3458400 | J17: =I17+J16 -> 4177250 | ... M17: =L17+M16 -> 7948600 | N17: =N16 -> 7948600
A19: Less: AWS Activate / Cloud Startup Credits (Est.) | B19: =IF(2<=9, 'Cloud & Infra'!B12, 0) -> 38000 | C19: =IF(3<=9, 'Cloud & Infra'!C12, 0) -> 38000 | D19: =IF(4<=9, 'Cloud & Infra'!D12, 0) -> 47000 | E19: =IF(5<=9, 'Cloud & Infra'!E12, 0) -> 54500 | F19: =IF(6<=9, 'Cloud & Infra'!F12, 0) -> 74000 | G19: =IF(7<=9, 'Cloud & Infra'!G12, 0) -> 89500 | H19: =IF(8<=9, 'Cloud & Infra'!H12, 0) -> 105000 | I19: =IF(9<=9, 'Cloud & Infra'!I12, 0) -> 105000 | J19: =IF(10<=9, 'Cloud & Infra'!J12, 0) -> 0 | K19: =IF(11<=9, 'Cloud & Infra'!K12, 0) -> 0 | L19: =IF(12<=9, 'Cloud & Infra'!L12, 0) -> 0 | M19: =IF(13<=9, 'Cloud & Infra'!M12, 0) -> 0 | N19: =SUM(B19:M19) -> 551000
A20: NET CASH BURN (AFTER CREDITS) | B20: =B16-B19 -> 498800 | C20: =C16-C19 -> 105000 | D20: =D16-D19 -> 127900 | E20: =E16-E19 -> 158350 | F20: =F16-F19 -> 203200 | G20: =G16-G19 -> 522100 | H20: =H16-H19 -> 706800 | I20: =I16-I19 -> 585250 | ... N20: =N16-N19 -> 7397600

Sheet Team Expansion
A1: HUMAN CAPITAL & ENGINEERING TEAM EXPANSION MATRIX
A2: Headcount Ramp, CTC Benchmarks (INR) & Month-by-Month Payroll Distribution
A4: Engineering / Product Role | B4: Role Type | C4: Seniority | D4: Start Month | E4: Monthly Base (₹) | F4: Annual CTC (₹ Lakhs) | G4: M1 | H4: M2 | I4: M3 | J4: M4 | K4: M5 | L4: M6 | M4: M7 | N4: M8 | O4: M9 | P4: M10 | Q4: M11 | R4: M12 | S4: 12M Total
A5: Senior Full-Stack & React Native Lead | B5: FTE | C5: Senior (5+ Yrs) | D5: M1 | E5: 120000 | F5: =E5*12/100000 -> 14.4 | G5: =IF(1>=1, $E5, 0) -> 120000 | H5: =IF(2>=1, $E5, 0) -> 120000 | I5: =IF(3>=1, $E5, 0) -> 120000 | J5: =IF(4>=1, $E5, 0) -> 120000 | K5: =IF(5>=1, $E5, 0) -> 120000 | L5: =IF(6>=1, $E5, 0) -> 120000 | M5: =IF(7>=1, $E5, 0) -> 120000 | N5: =IF(8>=1, $E5, 0) -> 120000 | O5: =IF(9>=1, $E5, 0) -> 120000 | P5: =IF(10>=1, $E5, 0) -> 120000 | Q5: =IF(11>=1, $E5, 0) -> 120000 | R5: =IF(12>=1, $E5, 0) -> 120000 | S5: =SUM(G5:R5) -> 1440000
A6: Backend & Distributed Systems Engineer | B6: Contract -> FTE | C6: Senior (4+ Yrs) | D6: M1 | E6: 60000 | F6: =E6*12/100000 -> 7.2 | G6: =IF(1>=1, $E6, 0) -> 60000 | H6: =IF(2>=1, $E6, 0) -> 60000 | I6: =IF(3>=1, $E6, 0) -> 60000 | J6: =IF(4>=1, $E6, 0) -> 60000 | K6: =IF(5>=1, $E6, 0) -> 60000 | L6: =IF(6>=1, $E6, 0) -> 60000 | M6: =IF(7>=1, $E6, 0) -> 60000 | N6: =IF(8>=1, $E6, 0) -> 60000 | O6: =IF(9>=1, $E6, 0) -> 60000 | P6: =IF(10>=1, $E6, 0) -> 60000 | Q6: =IF(11>=1, $E6, 0) -> 60000 | R6: =IF(12>=1, $E6, 0) -> 60000 | S6: =SUM(G6:R6) -> 720000
A7: UI/UX & Product Design Specialist | B7: Contractor | C7: Mid-Senior | D7: M1 | E7: 40000 | F7: =E7*12/100000 -> 4.8 | G7: =IF(1>=1, $E7, 0) -> 40000 | H7: =IF(2>=1, $E7, 0) -> 40000 | I7: =IF(3>=1, $E7, 0) -> 40000 | J7: =IF(4>=1, $E7, 0) -> 40000 | K7: =IF(5>=1, $E7, 0) -> 40000 | L7: =IF(6>=1, $E7, 0) -> 40000 | M7: =IF(7>=1, $E7, 0) -> 40000 | N7: =IF(8>=1, $E7, 0) -> 40000 | O7: =IF(9>=1, $E7, 0) -> 40000 | P7: =IF(10>=1, $E7, 0) -> 40000 | Q7: =IF(11>=1, $E7, 0) -> 40000 | R7: =IF(12>=1, $E7, 0) -> 40000 | S7: =SUM(G7:R7) -> 480000
A8: QA Engineer & Automation Tester | B8: Contractor | C8: Mid (2+ Yrs) | D8: M1 | E8: 25000 | F8: =E8*12/100000 -> 3 | G8: =IF(1>=1, $E8, 0) -> 25000 | H8: =IF(2>=1, $E8, 0) -> 25000 | I8: =IF(3>=1, $E8, 0) -> 25000 | J8: =IF(4>=1, $E8, 0) -> 25000 | K8: =IF(5>=1, $E8, 0) -> 25000 | L8: =IF(6>=1, $E8, 0) -> 25000 | M8: =IF(7>=1, $E8, 0) -> 25000 | N8: =IF(8>=1, $E8, 0) -> 25000 | O8: =IF(9>=1, $E8, 0) -> 25000 | P8: =IF(10>=1, $E8, 0) -> 25000 | Q8: =IF(11>=1, $E8, 0) -> 25000 | R8: =IF(12>=1, $E8, 0) -> 25000 | S8: =SUM(G8:R8) -> 300000
A9: Lead Mobile Native Engineer (iOS/Android) | B9: FTE (Expansion) | C9: Staff/Lead | D9: M5 | E9: 130000 | F9: =E9*12/100000 -> 15.6 | G9: =IF(1>=5, $E9, 0) -> 0 | H9: =IF(2>=5, $E9, 0) -> 0 | I9: =IF(3>=5, $E9, 0) -> 0 | J9: =IF(4>=5, $E9, 0) -> 0 | K9: =IF(5>=5, $E9, 0) -> 130000 | L9: =IF(6>=5, $E9, 0) -> 130000 | M9: =IF(7>=5, $E9, 0) -> 130000 | N9: =IF(8>=5, $E9, 0) -> 130000 | O9: =IF(9>=5, $E9, 0) -> 130000 | P9: =IF(10>=5, $E9, 0) -> 130000 | Q9: =IF(11>=5, $E9, 0) -> 130000 | R9: =IF(12>=5, $E9, 0) -> 130000 | S9: =SUM(G9:R9) -> 1040000
A10: Senior Backend & Infrastructure Engineer | B10: FTE (Expansion) | C10: Senior (4+ Yrs) | D10: M5 | E10: 130000 | F10: =E10*12/100000 -> 15.6 | G10: =IF(1>=5, $E10, 0) -> 0 | H10: =IF(2>=5, $E10, 0) -> 0 | I10: =IF(3>=5, $E10, 0) -> 0 | J10: =IF(4>=5, $E10, 0) -> 0 | K10: =IF(5>=5, $E10, 0) -> 130000 | L10: =IF(6>=5, $E10, 0) -> 130000 | M10: =IF(7>=5, $E10, 0) -> 130000 | N10: =IF(8>=5, $E10, 0) -> 130000 | O10: =IF(9>=5, $E10, 0) -> 130000 | P10: =IF(10>=5, $E10, 0) -> 130000 | Q10: =IF(11>=5, $E10, 0) -> 130000 | R10: =IF(12>=5, $E10, 0) -> 130000 | S10: =SUM(G10:R10) -> 1040000
A11: Full-time Product Designer (UI/UX) | B11: FTE (Expansion) | C11: Mid (3+ Yrs) | D11: M5 | E11: 70000 | F11: =E11*12/100000 -> 8.4 | G11: =IF(1>=5, $E11, 0) -> 0 | H11: =IF(2>=5, $E11, 0) -> 0 | I11: =IF(3>=5, $E11, 0) -> 0 | J11: =IF(4>=5, $E11, 0) -> 0 | K11: =IF(5>=5, $E11, 0) -> 70000 | L11: =IF(6>=5, $E11, 0) -> 70000 | M11: =IF(7>=5, $E11, 0) -> 70000 | N11: =IF(8>=5, $E11, 0) -> 70000 | O11: =IF(9>=5, $E11, 0) -> 70000 | P11: =IF(10>=5, $E11, 0) -> 70000 | Q11: =IF(11>=5, $E11, 0) -> 70000 | R11: =IF(12>=5, $E11, 0) -> 70000 | S11: =SUM(G11:R11) -> 560000
A12: Cloud Security & DevOps Specialist | B12: Retainer | C12: Expert/Consultant | D12: M5 | E12: 50000 | F12: =E12*12/100000 -> 6 | G12: =IF(1>=5, $E12, 0) -> 0 | H12: =IF(2>=5, $E12, 0) -> 0 | I12: =IF(3>=5, $E12, 0) -> 0 | J12: =IF(4>=5, $E12, 0) -> 0 | K12: =IF(5>=5, $E12, 0) -> 50000 | L12: =IF(6>=5, $E12, 0) -> 50000 | M12: =IF(7>=5, $E12, 0) -> 50000 | N12: =IF(8>=5, $E12, 0) -> 50000 | O12: =IF(9>=5, $E12, 0) -> 50000 | P12: =IF(10>=5, $E12, 0) -> 50000 | Q12: =IF(11>=5, $E12, 0) -> 50000 | R12: =IF(12>=5, $E12, 0) -> 50000 | S12: =SUM(G12:R12) -> 400000
A13: QA Automation Engineer (Full-time) | B13: FTE (Expansion) | C13: Mid (3+ Yrs) | D13: M6 | E13: 60000 | F13: =E13*12/100000 -> 7.2 | G13: =IF(1>=6, $E13, 0) -> 0 | H13: =IF(2>=6, $E13, 0) -> 0 | I13: =IF(3>=6, $E13, 0) -> 0 | J13: =IF(4>=6, $E13, 0) -> 0 | K13: =IF(5>=6, $E13, 0) -> 0 | L13: =IF(6>=6, $E13, 0) -> 60000 | M13: =IF(7>=6, $E13, 0) -> 60000 | N13: =IF(8>=6, $E13, 0) -> 60000 | O13: =IF(9>=6, $E13, 0) -> 60000 | P13: =IF(10>=6, $E13, 0) -> 60000 | Q13: =IF(11>=6, $E13, 0) -> 60000 | R13: =IF(12>=6, $E13, 0) -> 60000 | S13: =SUM(G13:R13) -> 420000
A14: Customer Tech Ops & Integration Associate | B14: FTE (Expansion) | C14: Junior-Mid | D14: M6 | E14: 35000 | F14: =E14*12/100000 -> 4.2 | G14: =IF(1>=6, $E14, 0) -> 0 | H14: =IF(2>=6, $E14, 0) -> 0 | I14: =IF(3>=6, $E14, 0) -> 0 | J14: =IF(4>=6, $E14, 0) -> 0 | K14: =IF(5>=6, $E14, 0) -> 0 | L14: =IF(6>=6, $E14, 0) -> 35000 | M14: =IF(7>=6, $E14, 0) -> 35000 | N14: =IF(8>=6, $E14, 0) -> 35000 | O14: =IF(9>=6, $E14, 0) -> 35000 | P14: =IF(10>=6, $E14, 0) -> 35000 | Q14: =IF(11>=6, $E14, 0) -> 35000 | R14: =IF(12>=6, $E14, 0) -> 35000 | S14: =SUM(G14:R14) -> 245000
A16: Active Headcount (FTE + Retainers) | G16: =COUNTIF(G5:G14, ">0") -> 4 | H16: =COUNTIF(H5:H14, ">0") -> 4 | I16: =COUNTIF(I5:I14, ">0") -> 4 | J16: =COUNTIF(J5:J14, ">0") -> 4 | K16: =COUNTIF(K5:K14, ">0") -> 8 | L16: =COUNTIF(L5:L14, ">0") -> 10 | M16: =COUNTIF(M5:M14, ">0") -> 10 | N16: =COUNTIF(N5:N14, ">0") -> 10 | ... R16: =COUNTIF(R5:R14, ">0") -> 10 | S16: =MAX(G16:R16) -> 10
A20: TOTAL MONTHLY ENGINEERING & PRODUCT PAYROLL | G20: =SUM(G5:G14) -> 245000 | H20: =SUM(H5:H14) -> 245000 | I20: =SUM(I5:I14) -> 245000 | J20: =SUM(J5:J14) -> 245000 | K20: =SUM(K5:K14) -> 625000 | L20: =SUM(L5:L14) -> 720000 | M20: =SUM(M5:M14) -> 720000 | N20: =SUM(N5:N14) -> 720000 | ... S20: =SUM(S5:S14) -> 6645000

Sheet Cloud & Infra
A1: CLOUD INFRASTRUCTURE, DATABASE & HOSTING BUDGET
A2: AWS Architecture, Database Instances, Global Edge Hosting & Observability
A4: Infrastructure Component | B4: M1 | C4: M2 | D4: M3 | E4: M4 | F4: M5 | G4: M6 | H4: M7 | I4: M8 | J4: M9 | K4: M10 | L4: M11 | M4: M12 | N4: 12M Total
A5: Application Edge Hosting & CDN (Vercel / AWS Amplify) | B5: 3500 | C5: 3500 | D5: 4500 | E5: 5000 | F5: 8500 | G5: 10000 | H5: 12500 | I5: 12500 | J5: 14000 | K5: 15000 | L5: 15000 | M5: 15000 | N5: =SUM(B5:M5) -> 119000
A6: Compute & Microservices (AWS ECS Fargate / EC2) | B6: 12000 | C6: 12000 | D6: 15000 | E6: 18000 | F6: 25000 | G6: 30000 | H6: 35000 | I6: 35000 | J6: 38000 | K6: 40000 | L6: 42000 | M6: 45000 | N6: =SUM(B6:M6) -> 347000
A7: Database & High Availability (Supabase / RDS Postgres + Redis) | B7: 10000 | C7: 10000 | D7: 12000 | E7: 14000 | F7: 18000 | G7: 22000 | H7: 25000 | I7: 25000 | J7: 28000 | K7: 30000 | L7: 30000 | M7: 32000 | N7: =SUM(B7:M7) -> 256000
A8: Storage & Encrypted KYC S3 Buckets (AWS S3 + CloudFront) | B8: 2500 | C8: 2500 | D8: 3000 | E8: 3500 | F8: 4500 | G8: 5500 | H8: 6500 | I8: 6500 | J8: 7500 | K8: 8000 | L8: 8500 | M8: 9000 | N8: =SUM(B8:M8) -> 67500
A9: Logging, APM & Observability (Datadog / Sentry / BetterStack) | B9: 6500 | C9: 6500 | D9: 8000 | E9: 9500 | F9: 12000 | G9: 15000 | H9: 18000 | I9: 18000 | J9: 20000 | K9: 20000 | L9: 22000 | M9: 22000 | N9: =SUM(B9:M9) -> 177500
A10: CI/CD Pipeline & Automated Build Runners | B10: 2000 | C10: 2000 | D10: 2500 | E10: 2500 | F10: 3500 | G10: 4000 | H10: 4500 | I10: 4500 | J10: 5000 | K10: 5000 | L10: 5000 | M10: 5000 | N10: =SUM(B10:M10) -> 45500
A11: Disaster Recovery & Redundant Backups | B11: 1500 | C11: 1500 | D11: 2000 | E11: 2000 | F11: 2500 | G11: 3000 | H11: 3500 | I11: 3500 | J11: 4000 | K11: 4000 | L11: 4000 | M11: 4000 | N11: =SUM(B11:M11) -> 35500
A12: TOTAL CLOUD INFRASTRUCTURE & HOSTING | B12: =SUM(B5:B11) -> 38000 | C12: =SUM(C5:C11) -> 38000 | D12: =SUM(D5:D11) -> 47000 | E12: =SUM(E5:E11) -> 54500 | F12: =SUM(F5:F11) -> 74000 | G12: =SUM(G5:G11) -> 89500 | H12: =SUM(H5:H11) -> 105000 | I12: =SUM(I5:I11) -> 105000 | ... N12: =SUM(N5:N11) -> 1048000

Sheet Fintech APIs & Rails
A1: FINTECH RAILS, KYC VERIFICATION & PAYMENT GATEWAYS
A2: UPI Autopay Mandates, Aadhaar/PAN KYC Checks, SMS/WhatsApp Gateways & Ticker Data
A4: Integration / Partner API | B4: M1 | C4: M2 | D4: M3 | E4: M4 | F4: M5 | G4: M6 | H4: M7 | I4: M8 | J4: M9 | K4: M10 | L4: M11 | M4: M12 | N4: 12M Total
A5: Aadhaar e-KYC & DigiLocker Verification (Hyperverge/IDfy) | B5: 8000 | C5: 10000 | D5: 12000 | E5: 15000 | F5: 22000 | G5: 28000 | H5: 35000 | I5: 40000 | J5: 45000 | K5: 48000 | L5: 50000 | M5: 52000 | N5: =SUM(B5:M5) -> 365000
A6: PAN Verification & Fraud Screening API | B6: 4000 | C6: 5000 | D6: 6000 | E6: 7500 | F6: 10000 | G6: 13000 | H6: 16000 | I6: 18000 | J6: 20000 | K6: 22000 | L6: 23000 | M6: 24000 | N6: =SUM(B6:M6) -> 168500
A7: UPI Autopay & E-Mandate Processing (Cashfree/Razorpay) | B7: 12000 | C7: 15000 | D7: 18000 | E7: 22000 | F7: 32000 | G7: 42000 | H7: 52000 | I7: 58000 | J7: 65000 | K7: 70000 | L7: 72000 | M7: 75000 | N7: =SUM(B7:M7) -> 533000
A8: SMS & WhatsApp OTP Authentication (MSG91 / Gupshup) | B8: 6000 | C8: 7000 | D8: 8500 | E8: 10000 | F8: 15000 | G8: 19000 | H8: 24000 | I8: 27000 | J8: 30000 | K8: 32000 | L8: 34000 | M8: 36000 | N8: =SUM(B8:M8) -> 248500
A9: Live Crypto Market Data Feed (CoinGecko Pro API) | B9: 11000 | C9: 11000 | D9: 11000 | E9: 11000 | F9: 15000 | G9: 15000 | H9: 15000 | I9: 18000 | J9: 18000 | K9: 18000 | L9: 18000 | M9: 18000 | N9: =SUM(B9:M9) -> 179000
A10: Transactional Emails & Notification Webhooks (Resend/SES) | B10: 2000 | C10: 2000 | D10: 2500 | E10: 2500 | F10: 3500 | G10: 4000 | H10: 4500 | I10: 5000 | J10: 5500 | K10: 6000 | L10: 6000 | M10: 6500 | N10: =SUM(B10:M10) -> 50000
A11: Exchange Liquidity / Custody Partner Webhooks & Nodes | B11: 5000 | C11: 5000 | D11: 6000 | E11: 7000 | F11: 10000 | G11: 12000 | H11: 15000 | I11: 18000 | J11: 20000 | K11: 22000 | L11: 24000 | M11: 25000 | N11: =SUM(B11:M11) -> 169000
A12: Bank Payout & Withdrawal Rails (Instant IMPS/NEFT) | B12: 3000 | C12: 4000 | D12: 5000 | E12: 6000 | F12: 9000 | G12: 12000 | H12: 15000 | I12: 17000 | J12: 19000 | K12: 20000 | L12: 21000 | M12: 22000 | N12: =SUM(B12:M12) -> 153000
A14: TOTAL FINTECH RAILS & INTEGRATION APIS | B14: =SUM(B5:B12) -> 51000 | C14: =SUM(C5:C12) -> 59000 | D14: =SUM(D5:D12) -> 69000 | E14: =SUM(E5:E12) -> 81000 | F14: =SUM(F5:F12) -> 116500 | G14: =SUM(G5:G12) -> 145000 | H14: =SUM(H5:H12) -> 176500 | I14: =SUM(I5:I12) -> 201000 | ... N14: =SUM(N5:N12) -> 1866000

Sheet Security & Compliance
A1: SECURITY AUDITS, VAPT & FIU-IND COMPLIANCE BUDGET
A2: CERT-In Audits, Penetration Testing, AML Tooling, FIU Reporting & Legal Tech Retainers
A4: Security & Compliance Milestone | B4: M1 | C4: M2 | D4: M3 | E4: M4 | F4: M5 | G4: M6 | H4: M7 | I4: M8 | J4: M9 | K4: M10 | L4: M11 | M4: M12 | N4: 12M Total
A5: CERT-In Certified VAPT Audit (Pre-Launch & Bi-Annual) | B5: 250000 | C5: 0 | D5: 0 | E5: 0 | F5: 0 | G5: 0 | H5: 150000 | I5: 0 | J5: 0 | K5: 0 | L5: 0 | M5: 0 | N5: =SUM(B5:M5) -> 400000
A6: FIU-IND AML Screening & Sanction Check Software | B6: 10000 | C6: 10000 | D6: 10000 | E6: 10000 | F6: 12000 | G6: 12000 | H6: 12000 | I6: 12000 | J6: 15000 | K6: 15000 | L6: 15000 | M6: 15000 | N6: =SUM(B6:M6) -> 148000
A7: Smart Contract / Non-Custodial Vault Logic Audit | B7: 50000 | C7: 0 | D7: 0 | E7: 0 | F7: 0 | G7: 0 | H7: 0 | I7: 0 | J7: 0 | K7: 0 | L7: 0 | M7: 0 | N7: =SUM(B7:M7) -> 50000
A8: Cloudflare Enterprise DDoS Protection & Wildcard SSL | B8: 4500 | C8: 4500 | D8: 4500 | E8: 4500 | F8: 4500 | G8: 4500 | H8: 4500 | I8: 4500 | J8: 4500 | K8: 4500 | L8: 4500 | M8: 4500 | N8: =SUM(B8:M8) -> 54000
A9: Legal Tech, ToS & FIU Disclosures Retainer | B9: 40000 | C9: 0 | D9: 0 | E9: 15000 | F9: 0 | G9: 15000 | H9: 0 | I9: 15000 | J9: 0 | K9: 15000 | L9: 0 | M9: 15000 | N9: =SUM(B9:M9) -> 115000
A10: Data Protection & ISO 27001 Readiness Prep | B10: 0 | C10: 0 | D10: 10000 | E10: 10000 | F10: 15000 | G10: 15000 | H10: 15000 | I10: 15000 | J10: 20000 | K10: 20000 | L10: 20000 | M10: 20000 | N10: =SUM(B10:M10) -> 160000
A12: TOTAL SECURITY, VAPT & COMPLIANCE | B12: =SUM(B5:B10) -> 354500 | C12: =SUM(C5:C10) -> 14500 | D12: =SUM(D5:D10) -> 24500 | E12: =SUM(E5:E10) -> 39500 | F12: =SUM(F5:F10) -> 31500 | G12: =SUM(G5:G10) -> 46500 | H12: =SUM(H5:H10) -> 181500 | I12: =SUM(I5:I10) -> 46500 | ... N12: =SUM(N5:N10) -> 927000

Sheet Tooling & Licences
A1: DEVELOPER ACCOUNTS, SOFTWARE LICENCES & PRODUCTIVITY
A2: App Store, Google Play, GitHub Enterprise, Figma, Linear & Team Productivity
A4: Software Tool / Licence | B4: M1 | C4: M2 | D4: M3 | E4: M4 | F4: M5 | G4: M6 | H4: M7 | I4: M8 | J4: M9 | K4: M10 | L4: M11 | M4: M12 | N4: 12M Total
A5: Apple Developer Enterprise Program ($99/year) | B5: 8900 | C5: 0 | D5: 0 | E5: 0 | F5: 0 | G5: 0 | H5: 0 | I5: 0 | J5: 0 | K5: 0 | L5: 0 | M5: 0 | N5: =SUM(B5:M5) -> 8900
A6: Google Play Developer Console ($25 one-time) | B6: 2100 | C6: 0 | D6: 0 | E6: 0 | F6: 0 | G6: 0 | H6: 0 | I6: 0 | J6: 0 | K6: 0 | L6: 0 | M6: 0 | N6: =SUM(B6:M6) -> 2100
A7: GitHub Enterprise & Copilot Team Licences | B7: 4500 | C7: 4500 | D7: 4500 | E7: 4500 | F7: 7500 | G7: 7500 | H7: 7500 | I7: 7500 | J7: 7500 | K7: 7500 | L7: 7500 | M7: 7500 | N7: =SUM(B7:M7) -> 78000
A8: Figma Organization (UI/UX Systems & Design Tokens) | B8: 3000 | C8: 3000 | D8: 3000 | E8: 3000 | F8: 6000 | G8: 6000 | H8: 6000 | I8: 6000 | J8: 6000 | K8: 6000 | L8: 6000 | M8: 6000 | N8: =SUM(B8:M8) -> 60000
A9: Linear, Notion & Postman Team Workspaces | B9: 4000 | C9: 4000 | D9: 4000 | E9: 4000 | F9: 6500 | G9: 6500 | H9: 6500 | I9: 6500 | J9: 6500 | K9: 6500 | L9: 6500 | M9: 6500 | N9: =SUM(B9:M9) -> 68000
A10: Google Workspace & Domain Inboxes (10 Accounts) | B10: 5500 | C10: 5500 | D10: 5500 | E10: 5500 | F10: 8000 | G10: 8000 | H10: 8000 | I10: 8000 | J10: 8000 | K10: 8000 | L10: 8000 | M10: 8000 | N10: =SUM(B10:M10) -> 86000
A11: TestFlight & Android Internal App Distribution Tools | B11: 1500 | C11: 1500 | D11: 1500 | E11: 1500 | F11: 2000 | G11: 2000 | H11: 2000 | I11: 2000 | J11: 2000 | K11: 2000 | L11: 2000 | M11: 2000 | N11: =SUM(B11:M11) -> 22000
A12: Code Signing & Production SSL Certificates | B12: 15000 | C12: 0 | D12: 0 | E12: 0 | F12: 0 | G12: 0 | H12: 0 | I12: 0 | J12: 0 | K12: 0 | L12: 0 | M12: 0 | N12: =SUM(B12:M12) -> 15000
A14: TOTAL SOFTWARE LICENCES & TOOLING | B14: =SUM(B5:B12) -> 44500 | C14: =SUM(C5:C12) -> 18500 | D14: =SUM(D5:D12) -> 18500 | E14: =SUM(E5:E12) -> 18500 | F14: =SUM(F5:F12) -> 30000 | G14: =SUM(G5:G12) -> 30000 | H14: =SUM(H5:H12) -> 30000 | I14: =SUM(I5:I12) -> 30000 | ... N14: =SUM(N5:N12) -> 340000

Sheet Unit Economics & Scenarios
A1: MARGINAL TECH UNIT ECONOMICS & SCALE SCENARIOS
A2: One-Time Customer Onboarding Cost vs Monthly Active SIP Operational Cost
A4: One-Time Onboarding & KYC Cost per User | E4: Scale Simulation Matrix
A5: Verification / Onboarding Step | B5: Vendor / Method | C5: Cost per User (INR) | E5: Active SIP Users | F5: Monthly Variable Tech (₹) | G5: Annualized Variable Cost
A6: Mobile OTP Authentication (2 attempts) | B6: MSG91 Gateway | C6: 0.3 | E6: 1000 | F6: =E6*$C$19 -> 4800 | G6: =F6*12 -> 57600
A7: DigiLocker Aadhaar e-KYC Verification | B7: Hyperverge / IDfy | C7: 1.5 | E7: 5000 | F7: =E7*$C$19 -> 24000 | G7: =F7*12 -> 288000
A8: Real-time PAN Database Validation | B8: NSDL / Income Tax API | C8: 1 | E8: 15000 | F8: =E8*$C$19 -> 72000 | G8: =F8*12 -> 864000
A9: Liveness Check & Anti-Fraud Face Match | B9: AI Verification Engine | C9: 4.5 | E9: 50000 | F9: =E9*$C$19 -> 240000 | G9: =F9*12 -> 2880000
A10: UPI Autopay Mandate Registration Setup | B10: Cashfree / Razorpay | C10: 5 | E10: 100000 | F10: =E10*$C$19 -> 480000 | G10: =F10*12 -> 5760000
A11: Encrypted Document Storage & DB Indexing | B11: AWS S3 & Postgres | C11: 1.2
A12: TOTAL ONE-TIME ONBOARDING TECH COST | C12: =SUM(C6:C11) -> 13.5
A14: Monthly Recurring Tech Cost per Active SIP User (30 Days)
A15: Recurring Service Line | B15: Frequency / Assumption | C15: Cost per Mo (INR)
A16: UPI Recurring Autopay Execution | B16: 30 Daily Debits @ ₹0.12/debit | C16: 3.6
A17: Streak Milestones & Push Notifications | B17: FCM & WhatsApp Triggers | C17: 0.2
A18: Database Transaction Records & Rebalancing | B18: Postgres I/O & Compute | C18: 1
A19: TOTAL MONTHLY TECH RUN COST / ACTIVE INVESTOR | C19: =SUM(C16:C18) -> 4.8
